{
    "id": "log",
    "summary": "Logarithm to a base",
    "description": "Logarithm to the base `base` of the number `x` is defined to be the inverse function of taking b to the power of x.\n\nThe nodata value `null` is passed through and therefore gets propagated.",
    "categories": [
        "math > exponential & logarithmic"
    ],
    "parameter_order": ["x", "base"],
    "parameters": {
        "x": {
            "description": "A number to compute the logarithm for.",
            "schema": {
                "type": [
                    "number",
                    "null"
                ]
            },
            "required": true
        },
        "base": {
            "description": "The numerical base.",
            "schema": {
                "type": [
                    "number",
                    "null"
                ]
            },
            "required": true
        }
    },
    "returns": {
        "description": "The computed logarithm.",
        "schema": {
            "type": [
                "number",
                "null"
            ]
        }
    },
    "examples": [
        {
            "arguments": {
                "x": 10,
                "base": 10
            },
            "returns": 1
        },
        {
            "arguments": {
                "x": 2,
                "base": 2
            },
            "returns": 1
        },
        {
            "arguments": {
                "x": 4,
                "base": 2
            },
            "returns": 2
        },
        {
            "arguments": {
                "x": 1,
                "base": 16
            },
            "returns": 0
        }
    ],
    "links": [
        {
            "rel": "about",
            "href": "http://mathworld.wolfram.com/Logarithm.html",
            "title": "Logarithm explained by Wolfram MathWorld"
        }
    ]
}